amqp_framework/__init__.py
amqp_framework/abstract_consumer.py
amqp_framework/helpers.py
amqp_framework/http_status.py
amqp_framework/producer.py
amqp_framework/request.py
amqp_framework/response.py
amqp_framework-0.1.1.dist-info/METADATA
amqp_framework-0.1.1.dist-info/WHEEL
amqp_framework-0.1.1.dist-info/top_level.txt
amqp_framework-0.1.1.dist-info/RECORD
